Workbook

Sheet Dashboard
A1: PERSONAL FINANCE DASHBOARD
A2: Last Updated: June 06, 2026
A4: MONTHLY SUMMARY
A5: Total Income | B5: =Income!B20
A6: Total Expenses | B6: =Expenses!B18
A7: Net Savings | B7: =B6-B7
A8: Savings Rate | B8: =IF(B6>0,(B8/B6)*100,0)
A11: FINANCIAL HEALTH
A12: Active Loans | B12: =Loans!B14
A13: Total Loan Balance | B13: =Loans!B15
A14: Savings Goals Progress | B14: =Savings!B12
A15: Budget Status | B15: =IF(Dashboard!B8>0,IF(Dashboard!B8/Dashboard!B6>0.2,"On Track","Needs Attention"),"No Data")

Sheet Income
A1: MONTHLY INCOME & BUDGET
A3: INCOME SOURCES
A4: Source | B4: Budgeted | C4: Actual | D4: Variance | E4: Notes
A5: Salary | B5: 5000 | D5: =C5-B5 | E5: Primary income
A6: Freelance | B6: 500 | D6: =C6-B6
A7: Investments | B7: 200 | D7: =C7-B7
A8: Side Business | B8: 300 | D8: =C8-B8
A9: Other | B9: 100 | D9: =C9-B9
A10: Total Income | B10: =SUM(B5:B9) | C10: =SUM(C5:C9) | D10: =C10-B10
A12: BUDGET CATEGORIES
A13: Category | B13: Budgeted | C13: Spent | D13: Remaining | E13: Status
A14: Housing | B14: 1500 | D14: =B14-C14 | E14: =IF(C14>B14,"Over Budget",IF(C14=B14,"On Target","Under Budget"))
A15: Utilities | B15: 200 | D15: =B15-C15 | E15: =IF(C15>B15,"Over Budget",IF(C15=B15,"On Target","Under Budget"))
A16: Groceries | B16: 600 | D16: =B16-C16 | E16: =IF(C16>B16,"Over Budget",IF(C16=B16,"On Target","Under Budget"))
A17: Transportation | B17: 400 | D17: =B17-C17 | E17: =IF(C17>B17,"Over Budget",IF(C17=B17,"On Target","Under Budget"))
A18: Insurance | B18: 300 | D18: =B18-C18 | E18: =IF(C18>B18,"Over Budget",IF(C18=B18,"On Target","Under Budget"))
A19: Entertainment | B19: 200 | D19: =B19-C19 | E19: =IF(C19>B19,"Over Budget",IF(C19=B19,"On Target","Under Budget"))
A20: Dining Out | B20: 250 | D20: =B20-C20 | E20: =IF(C20>B20,"Over Budget",IF(C20=B20,"On Target","Under Budget"))
A21: Healthcare | B21: 150 | D21: =B21-C21 | E21: =IF(C21>B21,"Over Budget",IF(C21=B21,"On Target","Under Budget"))
A22: Personal Care | B22: 100 | D22: =B22-C22 | E22: =IF(C22>B22,"Over Budget",IF(C22=B22,"On Target","Under Budget"))
A23: Education | B23: 100 | D23: =B23-C23 | E23: =IF(C23>B23,"Over Budget",IF(C23=B23,"On Target","Under Budget"))
A24: Savings | B24: 500 | D24: =B24-C24 | E24: =IF(C24>B24,"Over Budget",IF(C24=B24,"On Target","Under Budget"))
A25: Miscellaneous | B25: 200 | D25: =B25-C25 | E25: =IF(C25>B25,"Over Budget",IF(C25=B25,"On Target","Under Budget"))
A26: Total Budget | B26: =SUM(B14:B25) | C26: =SUM(C14:C25) | D26: =B26-C26
A28: MONTHLY SUMMARY
A29: Total Income | B29: =B10
A30: Total Budget | B30: =B26
A31: Remaining | B31: =B29-B30

Sheet Expenses
A1: EXPENSES TRACKER
A3: Date | B3: Category | C3: Description | D3: Amount | E3: Payment Method | F3: Receipt | G3: Notes | H3: Month
A4: 2026-06-01 | B4: Housing | C4: Monthly Rent | D4: 1500 | E4: Bank Transfer | F4: Yes | H4: June
A5: 2026-06-02 | B5: Groceries | C5: Weekly Shopping | D5: 145.5 | E5: Credit Card | F5: Yes | H5: June
A6: 2026-06-03 | B6: Utilities | C6: Electric Bill | D6: 85.2 | E6: Auto Pay | F6: Yes | H6: June
A7: 2026-06-05 | B7: Transportation | C7: Gas | D7: 55 | E7: Debit Card | F7: No | H7: June
A8: 2026-06-07 | B8: Dining Out | C8: Restaurant | D8: 42.5 | E8: Credit Card | F8: No | H8: June
A9: 2026-06-10 | B9: Healthcare | C9: Pharmacy | D9: 28.9 | E9: Debit Card | F9: Yes | H9: June
A10: 2026-06-12 | B10: Entertainment | C10: Movie Tickets | D10: 32 | E10: Credit Card | F10: No | H10: June
A11: 2026-06-15 | B11: Groceries | C11: Weekly Shopping | D11: 132.75 | E11: Credit Card | F11: Yes | H11: June
A12: 2026-06-18 | B12: Personal Care | C12: Haircut | D12: 45 | E12: Cash | F12: No | H12: June
A13: 2026-06-20 | B13: Utilities | C13: Internet | D13: 65 | E13: Auto Pay | F13: Yes | H13: June
A14: 2026-06-22 | B14: Dining Out | C14: Coffee Shop | D14: 18.5 | E14: Credit Card | F14: No | H14: June
A15: 2026-06-25 | B15: Transportation | C15: Parking | D15: 25 | E15: Debit Card | F15: No | H15: June
A17: TOTAL EXPENSES | D17: =SUM(D4:D16)
A19: EXPENSES BY CATEGORY
A20: Category | B20: Total Spent | C20: % of Total | D20: Budget | E20: Remaining
A21: Housing | B21: =SUMIF(B:B,A21,D:D) | C21: =IF(D17>0,B21/D17*100,0) | D21: =VLOOKUP(A21,Income!A14:B25,2,FALSE) | E21: =D21-B21
A22: Utilities | B22: =SUMIF(B:B,A22,D:D) | C22: =IF(D17>0,B22/D17*100,0) | D22: =VLOOKUP(A22,Income!A14:B25,2,FALSE) | E22: =D22-B22
A23: Groceries | B23: =SUMIF(B:B,A23,D:D) | C23: =IF(D17>0,B23/D17*100,0) | D23: =VLOOKUP(A23,Income!A14:B25,2,FALSE) | E23: =D23-B23
A24: Transportation | B24: =SUMIF(B:B,A24,D:D) | C24: =IF(D17>0,B24/D17*100,0) | D24: =VLOOKUP(A24,Income!A14:B25,2,FALSE) | E24: =D24-B24
A25: Insurance | B25: =SUMIF(B:B,A25,D:D) | C25: =IF(D17>0,B25/D17*100,0) | D25: =VLOOKUP(A25,Income!A14:B25,2,FALSE) | E25: =D25-B25
A26: Entertainment | B26: =SUMIF(B:B,A26,D:D) | C26: =IF(D17>0,B26/D17*100,0) | D26: =VLOOKUP(A26,Income!A14:B25,2,FALSE) | E26: =D26-B26
A27: Dining Out | B27: =SUMIF(B:B,A27,D:D) | C27: =IF(D17>0,B27/D17*100,0) | D27: =VLOOKUP(A27,Income!A14:B25,2,FALSE) | E27: =D27-B27
A28: Healthcare | B28: =SUMIF(B:B,A28,D:D) | C28: =IF(D17>0,B28/D17*100,0) | D28: =VLOOKUP(A28,Income!A14:B25,2,FALSE) | E28: =D28-B28
A29: Personal Care | B29: =SUMIF(B:B,A29,D:D) | C29: =IF(D17>0,B29/D17*100,0) | D29: =VLOOKUP(A29,Income!A14:B25,2,FALSE) | E29: =D29-B29
A30: Education | B30: =SUMIF(B:B,A30,D:D) | C30: =IF(D17>0,B30/D17*100,0) | D30: =VLOOKUP(A30,Income!A14:B25,2,FALSE) | E30: =D30-B30
A31: Miscellaneous | B31: =SUMIF(B:B,A31,D:D) | C31: =IF(D17>0,B31/D17*100,0) | D31: =VLOOKUP(A31,Income!A14:B25,2,FALSE) | E31: =D31-B31

Sheet Loans
A1: LOANS MANAGER
A3: ACTIVE LOANS
A4: Loan Name | B4: Type | C4: Principal | D4: Interest Rate | E4: Term | F4: Monthly Payment | G4: Start Date | H4: Remaining Payments | I4: Total Paid | J4: Remaining Balance
A5: Car Loan | B5: Auto | C5: 25000 | D5: 5.5 | E5: 60 | F5: 477 | G5: 2024-01-15 | H5: 42 | I5: 4770 | J5: 20025
A6: Student Loan | B6: Education | C6: 35000 | D6: 4.2 | E6: 120 | F6: 357 | G6: 2023-06-01 | H6: 96 | I6: 8568 | J6: 29856
A7: Credit Card 1 | B7: Credit | C7: 3000 | D7: 19.99 | E7: 24 | F7: 150 | G7: 2025-03-01 | H7: 21 | I7: 1350 | J7: 1950
A9: TOTALS | C9: =SUM(C5:C7) | F9: =SUM(F5:F7) | I9: =SUM(I5:I7) | J9: =SUM(J5:J7)
A11: Active Loans | B11: =COUNTA(A5:A7)
A12: Total Outstanding Balance | B12: =J9
A13: Total Monthly Payments | B13: =F9
A14: =B11
B15: =B12
A17: LOAN PAYOFF TIMELINE
A18: Month | B18: Payment | C18: Principal | D18: Interest | E18: Balance
A19: Month 1 | B19: 477 | C19: =B19*(1-0.00458) | D19: =B19-C19 | E19: =IF(19=19,20025-B19,E18-B19)
A20: Month 2 | B20: 477 | C20: =B20*(1-0.00458) | D20: =B20-C20 | E20: =IF(20=19,20025-B20,E19-B20)
A21: Month 3 | B21: 477 | C21: =B21*(1-0.00458) | D21: =B21-C21 | E21: =IF(21=19,20025-B21,E20-B21)
A22: Month 4 | B22: 477 | C22: =B22*(1-0.00458) | D22: =B22-C22 | E22: =IF(22=19,20025-B22,E21-B22)
A23: Month 5 | B23: 477 | C23: =B23*(1-0.00458) | D23: =B23-C23 | E23: =IF(23=19,20025-B23,E22-B23)
A24: Month 6 | B24: 477 | C24: =B24*(1-0.00458) | D24: =B24-C24 | E24: =IF(24=19,20025-B24,E23-B24)
A25: Month 7 | B25: 477 | C25: =B25*(1-0.00458) | D25: =B25-C25 | E25: =IF(25=19,20025-B25,E24-B25)
A26: Month 8 | B26: 477 | C26: =B26*(1-0.00458) | D26: =B26-C26 | E26: =IF(26=19,20025-B26,E25-B26)
A27: Month 9 | B27: 477 | C27: =B27*(1-0.00458) | D27: =B27-C27 | E27: =IF(27=19,20025-B27,E26-B27)
A28: Month 10 | B28: 477 | C28: =B28*(1-0.00458) | D28: =B28-C28 | E28: =IF(28=19,20025-B28,E27-B28)
A29: Month 11 | B29: 477 | C29: =B29*(1-0.00458) | D29: =B29-C29 | E29: =IF(29=19,20025-B29,E28-B29)
A30: Month 12 | B30: 477 | C30: =B30*(1-0.00458) | D30: =B30-C30 | E30: =IF(30=19,20025-B30,E29-B30)

Sheet Savings
A1: SAVINGS TRACKER
A3: SAVINGS GOALS
A4: Goal Name | B4: Target Amount | C4: Current Amount | D4: Monthly Contribution | E4: Target Date | F4: Progress %
A5: Emergency Fund | B5: 15000 | C5: 8500 | D5: 500 | E5: 2026-12-31 | F5: =C5/B5*100
A6: Vacation | B6: 5000 | C6: 1200 | D6: 300 | E6: 2026-08-01 | F6: =C6/B6*100
A7: New Car Down Payment | B7: 10000 | C7: 3500 | D7: 400 | E7: 2027-06-01 | F7: =C7/B7*100
A8: Home Down Payment | B8: 50000 | C8: 15000 | D8: 800 | E8: 2029-01-01 | F8: =C8/B8*100
A9: Retirement | B9: 500000 | C9: 45000 | D9: 600 | E9: 2045-01-01 | F9: =C9/B9*100
A11: TOTALS | B11: =SUM(B5:B9) | C11: =SUM(C5:C9) | D11: =SUM(D5:D9)
A12: Overall Progress | B12: =C11/B11*100
A14: SAVINGS TRANSACTIONS
A15: Date | B15: Goal | C15: Type | D15: Amount | E15: Notes
A16: 2026-06-01 | B16: Emergency Fund | C16: Deposit | D16: 500 | E16: Monthly contribution
A17: 2026-06-01 | B17: Vacation | C17: Deposit | D17: 300 | E17: Monthly contribution
A18: 2026-06-01 | B18: New Car Down Payment | C18: Deposit | D18: 400 | E18: Monthly contribution
A19: 2026-06-05 | B19: Emergency Fund | C19: Interest | D19: 25.5 | E19: Interest earned
A20: 2026-06-15 | B20: Home Down Payment | C20: Deposit | D20: 800 | E20: Monthly contribution

Sheet Charts
A1: FINANCIAL VISUALIZATIONS
A3: Expense Breakdown by Category
A4: Category | B4: Amount
A5: Housing | B5: 1500
A6: Groceries | B6: 278
A7: Utilities | B7: 150
A8: Transportation | B8: 80
A9: Dining Out | B9: 61
A10: Entertainment | B10: 32
A11: Healthcare | B11: 29
A12: Personal Care | B12: 45
A18: Budget vs Actual
A19: Category | B19: Budget | C19: Actual
A20: Housing | B20: 1500 | C20: 1500
A21: Groceries | B21: 600 | C21: 278
A22: Utilities | B22: 200 | C22: 150
A23: Transportation | B23: 400 | C23: 80
A24: Entertainment | B24: 200 | C24: 32
A25: Dining Out | B25: 250 | C25: 61
A26: Healthcare | B26: 150 | C26: 29
A27: Savings | B27: 500 | C27: 2025
A33: Savings Goals Progress
A34: Goal | B34: Target | C34: Current
A35: Emergency Fund | B35: 15000 | C35: 8500
A36: Vacation | B36: 5000 | C36: 1200
A37: Car Down Payment | B37: 10000 | C37: 3500
A38: Home Down Payment | B38: 50000 | C38: 15000

Sheet Net Worth
A1: NET WORTH TRACKER
A3: ASSETS
A4: Asset | B4: Value | C4: Type | D4: Notes
A5: Checking Account | B5: 5000 | C5: Cash
A6: Savings Account | B6: 28500 | C6: Cash | D6: Total savings
A7: Emergency Fund | B7: 8500 | C7: Cash
A8: 401(k) | B8: 45000 | C8: Investment
A9: Brokerage Account | B9: 12000 | C9: Investment
A10: Car (Blue Book Value) | B10: 18000 | C10: Property
A11: Home | B11: 350000 | C11: Property | D11: Estimated value
A13: LIABILITIES
A14: Liability | B14: Amount | C14: Type | D14: Notes
A15: Car Loan | B15: 20025 | C15: Auto Loan
A16: Student Loan | B16: 29856 | C16: Education
A17: Credit Card Balance | B17: 1950 | C17: Credit
A18: Mortgage | B18: 280000 | C18: Home
A20: NET WORTH SUMMARY
A21: Total Assets | B21: =SUM(B5:B11)
A22: Total Liabilities | B22: =SUM(B15:B18)
A23: NET WORTH | B23: =B21-B22

Sheet Monthly Budget
A1: MONTHLY BUDGET CALENDAR - JUNE 2026
A3: WEEKLY BUDGET | F3: DAILY SPENDING TRACKER
A4: Week | B4: Income | C4: Fixed Expenses | D4: Variable Expenses | E4: Savings | F4: Date | G4: Spent | H4: Running Total
A5: Week 1 | B5: 1500 | C5: 1850 | D5: 200 | E5: 500 | F5: June 1 | H5: =G5
A6: Week 2 | B6: 1500 | C6: 0 | D6: 350 | E6: 500 | F6: June 2 | H6: =H5+G6
A7: Week 3 | B7: 1500 | C7: 0 | D7: 280 | E7: 500 | F7: June 3 | H7: =H6+G7
A8: Week 4 | B8: 1500 | C8: 0 | D8: 180 | E8: 500 | F8: June 4 | H8: =H7+G8
F9: June 5 | H9: =H8+G9
A10: Monthly Total | B10: =SUM(B5:B8) | C10: =SUM(C5:C8) | D10: =SUM(D5:D8) | E10: =SUM(E5:E8) | F10: June 6 | H10: =H9+G10
F11: June 7 | H11: =H10+G11
A12: IMPORTANT DATES | F12: June 8 | H12: =H11+G12
A13: Date | B13: Bill/Expense | C13: Amount | D13: Status | F13: June 9 | H13: =H12+G13
A14: June 1 | B14: Rent | C14: 1500 | D14: Paid | F14: June 10 | H14: =H13+G14
A15: June 3 | B15: Electric Bill | C15: 85 | D15: Paid | F15: June 11 | H15: =H14+G15
A16: June 10 | B16: Internet | C16: 65 | D16: Paid | F16: June 12 | H16: =H15+G16
A17: June 15 | B17: Car Payment | C17: 477 | D17: Due | F17: June 13 | H17: =H16+G17
A18: June 20 | B18: Student Loan | C18: 357 | D18: Due | F18: June 14 | H18: =H17+G18
A19: June 25 | B19: Credit Card Due | C19: 500 | D19: Due | F19: June 15 | H19: =H18+G19
F20: June 16 | H20: =H19+G20
F21: June 17 | H21: =H20+G21
F22: June 18 | H22: =H21+G22
F23: June 19 | H23: =H22+G23
F24: June 20 | H24: =H23+G24
F25: June 21 | H25: =H24+G25
F26: June 22 | H26: =H25+G26
F27: June 23 | H27: =H26+G27
F28: June 24 | H28: =H27+G28
F29: June 25 | H29: =H28+G29
F30: June 26 | H30: =H29+G30
F31: June 27 | H31: =H30+G31
... F34: June 30 | H34: =H33+G34
